fetchcode/__init__.py
fetchcode/package.py
fetchcode/package_util.py
fetchcode/package_versions.py
fetchcode/packagedcode_models.py
fetchcode/utils.py
fetchcode/data/ipkg_releases.json
fetchcode/data/udhcp_releases.json
fetchcode/vcs/__init__.py
fetchcode/vcs/apache-2.0.LICENSE
fetchcode/vcs/bsd-new.LICENSE
fetchcode/vcs/git.py
fetchcode/vcs/isc.LICENSE
fetchcode/vcs/lgpl-2.1-plus.LICENSE
fetchcode/vcs/mit.LICENSE
fetchcode/vcs/pip-AUTHORS.txt
fetchcode/vcs/pip.ABOUT
fetchcode/vcs/pip.LICENSE
fetchcode/vcs/python.LICENSE
fetchcode/vcs/pip/__init__.py
fetchcode/vcs/pip/__main__.py
fetchcode/vcs/pip/__pip-runner__.py
fetchcode/vcs/pip/py.typed
fetchcode/vcs/pip/_internal/__init__.py
fetchcode/vcs/pip/_internal/build_env.py
fetchcode/vcs/pip/_internal/cache.py
fetchcode/vcs/pip/_internal/configuration.py
fetchcode/vcs/pip/_internal/exceptions.py
fetchcode/vcs/pip/_internal/main.py
fetchcode/vcs/pip/_internal/pyproject.py
fetchcode/vcs/pip/_internal/self_outdated_check.py
fetchcode/vcs/pip/_internal/wheel_builder.py
fetchcode/vcs/pip/_internal/cli/__init__.py
fetchcode/vcs/pip/_internal/cli/autocompletion.py
fetchcode/vcs/pip/_internal/cli/base_command.py
fetchcode/vcs/pip/_internal/cli/cmdoptions.py
fetchcode/vcs/pip/_internal/cli/command_context.py
fetchcode/vcs/pip/_internal/cli/index_command.py
fetchcode/vcs/pip/_internal/cli/main.py
fetchcode/vcs/pip/_internal/cli/main_parser.py
fetchcode/vcs/pip/_internal/cli/parser.py
fetchcode/vcs/pip/_internal/cli/progress_bars.py
fetchcode/vcs/pip/_internal/cli/req_command.py
fetchcode/vcs/pip/_internal/cli/spinners.py
fetchcode/vcs/pip/_internal/cli/status_codes.py
fetchcode/vcs/pip/_internal/commands/__init__.py
fetchcode/vcs/pip/_internal/commands/cache.py
fetchcode/vcs/pip/_internal/commands/check.py
fetchcode/vcs/pip/_internal/commands/completion.py
fetchcode/vcs/pip/_internal/commands/configuration.py
fetchcode/vcs/pip/_internal/commands/debug.py
fetchcode/vcs/pip/_internal/commands/download.py
fetchcode-0.6.0.dist-info/AUTHORS.rst
fetchcode-0.6.0.dist-info/CHANGELOG.rst
fetchcode-0.6.0.dist-info/CODE_OF_CONDUCT.rst
fetchcode-0.6.0.dist-info/METADATA
fetchcode-0.6.0.dist-info/NOTICE
fetchcode-0.6.0.dist-info/WHEEL
fetchcode-0.6.0.dist-info/apache-2.0.LICENSE
fetchcode-0.6.0.dist-info/top_level.txt
fetchcode-0.6.0.dist-info/RECORD
